bslideshow/____fg_23.py
bslideshow/__init__.py
bslideshow/convert.py
bslideshow/director.py
bslideshow/downloader.py
bslideshow/photo.py
bslideshow/project.py
bslideshow/slideshow.py
bslideshow/slideshow2.py
bslideshow/slideshow_old.py
bslideshow/tool.py
bslideshow/tools.py
bslideshow-0.0.43.data/scripts/bs_addBanner
bslideshow-0.0.43.data/scripts/bs_addBanner.cmd
bslideshow-0.0.43.data/scripts/bs_animImages
bslideshow-0.0.43.data/scripts/bs_animImages.cmd
bslideshow-0.0.43.data/scripts/bs_banner
bslideshow-0.0.43.data/scripts/bs_banner.cmd
bslideshow-0.0.43.data/scripts/bs_bgmusic
bslideshow-0.0.43.data/scripts/bs_bgmusic.cmd
bslideshow-0.0.43.data/scripts/bs_encode
bslideshow-0.0.43.data/scripts/bs_encode.cmd
bslideshow-0.0.43.data/scripts/bs_fadeIn
bslideshow-0.0.43.data/scripts/bs_fadeIn.cmd
bslideshow-0.0.43.data/scripts/bs_fadeOut
bslideshow-0.0.43.data/scripts/bs_fadeOut.cmd
bslideshow-0.0.43.data/scripts/bs_footage
bslideshow-0.0.43.data/scripts/bs_footage.cmd
bslideshow-0.0.43.data/scripts/bs_frames
bslideshow-0.0.43.data/scripts/bs_frames.cmd
bslideshow-0.0.43.data/scripts/bs_info
bslideshow-0.0.43.data/scripts/bs_info.cmd
bslideshow-0.0.43.data/scripts/bs_project
bslideshow-0.0.43.data/scripts/bs_project.cmd
bslideshow-0.0.43.data/scripts/bs_scale
bslideshow-0.0.43.data/scripts/bs_scale.cmd
bslideshow-0.0.43.data/scripts/bs_split
bslideshow-0.0.43.data/scripts/bs_split.cmd
bslideshow-0.0.43.data/scripts/bs_transition.cmd
bslideshow-0.0.43.data/scripts/bs_update
bslideshow-0.0.43.data/scripts/bs_update.cmd
bslideshow-0.0.43.data/scripts/sbrowser
bslideshow-0.0.43.dist-info/DESCRIPTION.rst
bslideshow-0.0.43.dist-info/METADATA
bslideshow-0.0.43.dist-info/RECORD
bslideshow-0.0.43.dist-info/WHEEL
bslideshow-0.0.43.dist-info/metadata.json
bslideshow-0.0.43.dist-info/top_level.txt
