Metadata-Version: 2.0
Name: bslideshow
Version: 0.0.43
Summary: Python library for generate slideshow from blender.
Home-page: https://github.com/tuaplicacionpropia/bslideshow
Author: tuaplicacionpropia.com
Author-email: tuaplicacionpropia@gmail.com
License: MIT
Download-URL: https://github.com/tuaplicacionpropia/bslideshow/archive/master.zip
Keywords: video,slideshow,blender
Platform: any
Classifier: Development Status :: 4 - Beta
Classifier: License :: OSI Approved :: MIT License
Classifier: Programming Language :: Python
Classifier: Programming Language :: Python :: 2.7
Classifier: Intended Audience :: Developers
Classifier: Topic :: Multimedia :: Graphics
Requires-Dist: Pillow (>=3.4.2)
Requires-Dist: hjson (>=2.0.2)
Requires-Dist: requests (>=2.21.0)
Requires-Dist: sbrowser (>=0.0.22)
